LICENSE.Apachev2
LICENSE.GPLv3
LICENSE.LGPLv3
LICENSE.md
MANIFEST.in
README.md
on_install.py
on_publish.py
pyproject.toml
setup.py
akashi_cli/__init__.py
akashi_cli/__main__.py
akashi_cli/cli.py
akashi_cli/parser.py
akashi_cli/py.typed
akashi_cli/utils.py
akashi_core/__init__.py
akashi_core/_ak.py
akashi_core/color.py
akashi_core/config.py
akashi_core/probe.py
akashi_core/py.typed
akashi_core/time.py
akashi_core/utils.py
akashi_core/elem/__init__.py
akashi_core/elem/atom.py
akashi_core/elem/context.py
akashi_core/elem/lane.py
akashi_core/elem/uuid.py
akashi_core/elem/layer/__init__.py
akashi_core/elem/layer/audio.py
akashi_core/elem/layer/base.py
akashi_core/elem/layer/effect.py
akashi_core/elem/layer/image.py
akashi_core/elem/layer/shape.py
akashi_core/elem/layer/text.py
akashi_core/elem/layer/video.py
akashi_core/pysl/__init__.py
akashi_core/pysl/_gl.py
akashi_core/pysl/shader.py
akashi_core/pysl/compiler/__init__.py
akashi_core/pysl/compiler/ast.py
akashi_core/pysl/compiler/compiler.py
akashi_core/pysl/compiler/compiler_lambda.py
akashi_core/pysl/compiler/compiler_named.py
akashi_core/pysl/compiler/converter.py
akashi_core/pysl/compiler/evaluator.py
akashi_core/pysl/compiler/items.py
akashi_core/pysl/compiler/symbol.py
akashi_core/pysl/compiler/utils.py
akashi_engine.egg-info/PKG-INFO
akashi_engine.egg-info/SOURCES.txt
akashi_engine.egg-info/dependency_links.txt
akashi_engine.egg-info/entry_points.txt
akashi_engine.egg-info/requires.txt
akashi_engine.egg-info/top_level.txt
sdist_temp/akashi_encoder
sdist_temp/akashi_kernel
sdist_temp/akashi_renderer
sdist_temp/libakprobe.so
sdist_temp/credits/ffmpeg/COPYING.LGPLv3
sdist_temp/credits/fontawesome/LICENSE.txt
sdist_temp/credits/fswatch/COPYING
sdist_temp/credits/fswatch/LICENSE
sdist_temp/credits/glfw/LICENSE.md
sdist_temp/credits/glm/copying.txt
sdist_temp/credits/httplib/LICENSE
sdist_temp/credits/libpython/LICENSE
sdist_temp/credits/nlohmann_json/LICENSE.MIT
sdist_temp/credits/pulseaudio/LGPL
sdist_temp/credits/pulseaudio/LICENSE
sdist_temp/credits/pybind11/LICENSE
sdist_temp/credits/qt/LICENSE
sdist_temp/credits/spdlog/LICENSE
sdist_temp/lib/libakeval.so
sdist_temp/lib/libfswatch.so
sdist_temp/lib/libfswatch.so.6
